shared_multiprocess_queue/__init__.py
shared_multiprocess_queue/queue.py
shared_multiprocess_queue-0.1.5.dist-info/METADATA
shared_multiprocess_queue-0.1.5.dist-info/WHEEL
shared_multiprocess_queue-0.1.5.dist-info/top_level.txt
shared_multiprocess_queue-0.1.5.dist-info/RECORD
