Metadata-Version: 2.4
Name: shared-multiprocess-queue
Version: 0.1.5
Summary: A shared-memory based multiprocessing queue for cross-process communication
Author-email: Raymond Chastain <RaymondLC92@protonmail.com>
License: MIT
Keywords: python,package
Classifier: Development Status :: 4 - Beta
Classifier: Intended Audience :: Developers
Classifier: License :: OSI Approved :: MIT License
Classifier: Programming Language :: Python :: 3.13
Requires-Python: >=3.13.7
Requires-Dist: cloudpickle>=3.0.0
Requires-Dist: shared_memory_lock>=0.1.5
